emoji_diamond/__init__.py
emoji_diamond/stars.py
emoji_diamond-0.1.dist-info/METADATA
emoji_diamond-0.1.dist-info/WHEEL
emoji_diamond-0.1.dist-info/top_level.txt
emoji_diamond-0.1.dist-info/RECORD
