Metadata-Version: 2.4
Name: emoji-diamond
Version: 0.1
Summary: A Python package that generates a diamond shape using random emojis.
Home-page: https://github.com/OligoCodes/emoji_diamond
Author: Joseph Bonsu 🇬🇭
Author-email: your_email@example.com
Classifier: Programming Language :: Python :: 3
Classifier: License :: OSI Approved :: MIT License
Requires-Python: >=3.6
Dynamic: author
Dynamic: author-email
Dynamic: classifier
Dynamic: description
Dynamic: description-content-type
Dynamic: home-page
Dynamic: requires-python
Dynamic: summary
